sqlalchemy_rds_iam/__init__.py
sqlalchemy_rds_iam/exceptions.py
sqlalchemy_rds_iam/plugin.py
sqlalchemy_rds_iam_auth_plugin-0.1.0.dist-info/METADATA
sqlalchemy_rds_iam_auth_plugin-0.1.0.dist-info/WHEEL
sqlalchemy_rds_iam_auth_plugin-0.1.0.dist-info/entry_points.txt
sqlalchemy_rds_iam_auth_plugin-0.1.0.dist-info/top_level.txt
sqlalchemy_rds_iam_auth_plugin-0.1.0.dist-info/RECORD
