Metadata-Version: 2.4
Name: sqlalchemy-rds-iam-auth-plugin
Version: 0.1.0
Summary: SQLAlchemy plugin for AWS RDS IAM authentication
Author-email: Luca Santarella <luca.santarella+github@gmail.com>
License: MIT
Project-URL: Homepage, https://github.com/lucasantarella/sqlalchemy-rds-iam-auth-plugin
Project-URL: Documentation, https://sqlalchemy-rds-iam-auth-plugin.readthedocs.io
Project-URL: Repository, https://github.com/lucasantarella/sqlalchemy-rds-iam-auth-plugin
Project-URL: Issues, https://github.com/lucasantarella/sqlalchemy-rds-iam-auth-plugin/issues
Classifier: Development Status :: 3 - Alpha
Classifier: Intended Audience :: Developers
Classifier: License :: OSI Approved :: MIT License
Classifier: Programming Language :: Python :: 3
Classifier: Programming Language :: Python :: 3.8
Classifier: Programming Language :: Python :: 3.9
Classifier: Programming Language :: Python :: 3.10
Classifier: Programming Language :: Python :: 3.11
Classifier: Programming Language :: Python :: 3.12
Requires-Python: >=3.8
Requires-Dist: sqlalchemy<3.0,>=1.4
Requires-Dist: boto3>=1.26
Provides-Extra: dev
Requires-Dist: pytest>=7.0; extra == "dev"
Requires-Dist: pytest-cov>=4.0; extra == "dev"
Requires-Dist: black>=23.0; extra == "dev"
Requires-Dist: flake8>=6.0; extra == "dev"
Requires-Dist: mypy>=1.0; extra == "dev"
Requires-Dist: pre-commit>=3.0; extra == "dev"
Requires-Dist: PyMySQL>=1.0; extra == "dev"
Requires-Dist: tox>=4.0; extra == "dev"
Requires-Dist: moto[rds]>=4.0; extra == "dev"
Requires-Dist: isort>=5.0; extra == "dev"
Requires-Dist: build>=0.8; extra == "dev"
Requires-Dist: twine>=4.0; extra == "dev"
Provides-Extra: docs
Requires-Dist: sphinx>=5.0; extra == "docs"
Requires-Dist: sphinx-rtd-theme>=1.0; extra == "docs"
